genewalk/__init__.py
genewalk/cli.py
genewalk/deepwalk.py
genewalk/gene_lists.py
genewalk/get_indra_stmts.py
genewalk/null_distributions.py
genewalk/nx_mg_assembler.py
genewalk/perform_statistics.py
genewalk/plot.py
genewalk/resources.py
genewalk/results_template.html
genewalk/tests/__init__.py
genewalk/tests/test_assemblers.py
genewalk/tests/test_cli.py
genewalk/tests/test_deepwalk.py
genewalk/tests/test_gene_lists.py
genewalk/tests/test_indra_assembly.py
genewalk/tests/test_sif_assembler.py
genewalk/tests/test_visualize.py
genewalk/tests/util.py
genewalk-1.6.3.dist-info/LICENSE
genewalk-1.6.3.dist-info/METADATA
genewalk-1.6.3.dist-info/WHEEL
genewalk-1.6.3.dist-info/entry_points.txt
genewalk-1.6.3.dist-info/top_level.txt
genewalk-1.6.3.dist-info/RECORD
