Metadata-Version: 2.1
Name: genewalk
Version: 1.6.3
Summary: Determine gene function based on network embeddings.
Home-page: https://github.com/churchmanlab/genewalk
Author: Robert Ietswaart
Author-email: robert_ietswaart@hms.harvard.edu
License: UNKNOWN
Keywords: gene function,network,embedding
Platform: UNKNOWN
Classifier: Development Status :: 4 - Beta
Classifier: Environment :: Console
Classifier: Intended Audience :: Science/Research
Classifier: License :: OSI Approved :: BSD License
Classifier: Operating System :: OS Independent
Classifier: Programming Language :: Python :: 3.8
Classifier: Programming Language :: Python :: 3.9
Classifier: Programming Language :: Python :: 3.10
Classifier: Programming Language :: Python :: 3.11
Classifier: Topic :: Scientific/Engineering :: Bio-Informatics
Requires-Dist: numpy
Requires-Dist: pandas
Requires-Dist: networkx (>=2.1)
Requires-Dist: gensim (>=4.0.0)
Requires-Dist: goatools
Requires-Dist: scipy (>=1.3.0)
Requires-Dist: matplotlib
Requires-Dist: seaborn
Requires-Dist: plotly (>=4.0.0)
Provides-Extra: indra
Requires-Dist: indra ; extra == 'indra'
